LICENSE
MANIFEST.in
README
setup.py
dev/__init__.py
dev/devListScansWithXpcsBatchName.py
dev/ericExample.py
examples/__init__.py
pyimm/GetImmStartIndex.py
pyimm/OpenMultiImm.py
pyimm/__init__.py
pyimm/immheader.py
pyimm/plotmultiimm.py
pyimm.egg-info/PKG-INFO
pyimm.egg-info/SOURCES.txt
pyimm.egg-info/dependency_links.txt
pyimm.egg-info/top_level.txt
test/__init__.py
test/testGetImmStartPositions.py
test/testReadSpec.py
test/testimmheader.py